{"aNdeZOzawcq+GwXJMKd7qA==":"logo_gogoro-457x128.png","OxhBba/SzLkImaN60L2HaQ==":"logo_gogoro-1-457x128.png","y9WmtN7l2mIXK+7jxAVMOw==":"gogoro-sunset-2000x1125.jpg","3zgADJuHgi7aPyG0o0MOcw==":"gogoro-s-dynamic-rear-72dpi-2000x1500.jpg","LAk8lfG0DKl21SRPPebq4g==":"gogoro-s-front-72dpi-2000x1500.jpg","K9EBdR9CvgE9RsgdzUmqdg==":"gogoro-front-left-quarter-view-2000x1498.jpg","Lo4oRvO6rmiJk/jpNGJjLA==":"gogoro-smartscooter-dashboard-2000x1498.jpg","yTiCnIU3uDRNpy2cIKF3xA==":"gogoro%20plus%20all%20you-2000x1125.jpg","bDsofoyxtcshQMbJ03zJkw==":"gogoro-smartscooter-open-2000x1498.jpg","Ser9QP5zn0WV9vSKDukpbg==":"gostation2-1400x1050.jpg","QjsH+jcHCaMqshoMR0Icgw==":"gostation2-2000x1500.jpg"}